kanren/__init__.py
kanren/_version.py
kanren/assoccomm.py
kanren/constraints.py
kanren/core.py
kanren/facts.py
kanren/goals.py
kanren/graph.py
kanren/term.py
kanren/util.py
miniKanren-1.0.1.dist-info/LICENSE.txt
miniKanren-1.0.1.dist-info/METADATA
miniKanren-1.0.1.dist-info/WHEEL
miniKanren-1.0.1.dist-info/top_level.txt
miniKanren-1.0.1.dist-info/RECORD
