Metadata-Version: 2.1
Name: miniKanren
Version: 1.0.1
Summary: Relational programming in Python
Home-page: http://github.com/pythological/kanren
Maintainer: Brandon T. Willard
Maintainer-email: brandonwillard+kanren@gmail.com
License: BSD
Platform: UNKNOWN
Classifier: Development Status :: 5 - Production/Stable
Classifier: Intended Audience :: Science/Research
Classifier: Intended Audience :: Developers
Classifier: License :: OSI Approved :: BSD License
Classifier: Operating System :: OS Independent
Classifier: Programming Language :: Python
Classifier: Programming Language :: Python :: 3
Classifier: Programming Language :: Python :: 3.6
Classifier: Programming Language :: Python :: 3.7
Classifier: Programming Language :: Python :: 3.8
Classifier: Programming Language :: Python :: Implementation :: CPython
Classifier: Programming Language :: Python :: Implementation :: PyPy
Requires-Python: >=3.6
Requires-Dist: toolz
Requires-Dist: cons (>=0.4.0)
Requires-Dist: multipledispatch
Requires-Dist: etuples (>=0.3.1)
Requires-Dist: logical-unification (>=0.4.1)
